ptcolors/__init__.py
ptcolors/ptcolors.py
ptcolors-0.1.8.dist-info/LICENSE
ptcolors-0.1.8.dist-info/METADATA
ptcolors-0.1.8.dist-info/WHEEL
ptcolors-0.1.8.dist-info/top_level.txt
ptcolors-0.1.8.dist-info/RECORD
