Metadata-Version: 2.1
Name: ptcolors
Version: 0.1.8
Summary: A lightweight Python package for adding customizable terminal colors.
Home-page: https://github.com/ec-intl/ptcolors
Author: Elizabeth Consulting International Inc.
Author-email: info@ec-intl.com
License: Apache License 2.0
Project-URL: Homepage, https://github.com/ec-intl/ptcolors
Project-URL: Issues, https://github.com/ec-intl/ptcolors/issues
Classifier: Programming Language :: Python :: 3
Classifier: License :: OSI Approved :: Apache Software License
Classifier: Operating System :: OS Independent
Requires-Python: >=3.6
License-File: LICENSE
